pykolofinance/__init__.py
pykolofinance/athena/__init__.py
pykolofinance/athena/security.py
pykolofinance/audtilog/console.py
pykolofinance/audtilog/contrib.py
pykolofinance/audtilog/encoder.py
pykolofinance/audtilog/logger.py
pykolofinance/audtilog/mongo_connector.py
pykolofinance/audtilog/readme.md
pykolofinance/audtilog/tasks.py
pykolofinance/authentication.py
pykolofinance/common/__init__.py
pykolofinance/common/enums.py
pykolofinance/common/exceptions.py
pykolofinance/common/fields.py
pykolofinance/common/file_uploads.py
pykolofinance/common/filter.py
pykolofinance/common/helpers.py
pykolofinance/common/kgs.py
pykolofinance/common/models.py
pykolofinance/common/pagination.py
pykolofinance/common/permissions.py
pykolofinance/common/schema.py
pykolofinance/common/security.py
pykolofinance/common/serializers.py
pykolofinance/common/services.py
pykolofinance/common/views.py
pykolofinance/enums.py
pykolofinance/filters.py
pykolofinance/kyc/__init__.py
pykolofinance/kyc/identity/__init__.py
pykolofinance/kyc/identity/factory.py
pykolofinance/kyc/identity/providers/base.py
pykolofinance/kyc/identity/providers/dojah.py
pykolofinance/kyc/identity/providers/mock.py
pykolofinance/kyc/verifier.py
pykolofinance/middlewares.py
pykolofinance/permissions/__init__.py
pykolofinance/permissions/checker.py
pykolofinance/permissions/perm_list.py
pykolofinance/phlox/__init__.py
pykolofinance/phlox/permissions.py
pykolofinance/services/__init__.py
pykolofinance/services/auth.py
pykolofinance/services/base.py
pykolofinance-5.0.5.dist-info/METADATA
pykolofinance-5.0.5.dist-info/WHEEL
pykolofinance-5.0.5.dist-info/RECORD
