Metadata-Version: 2.3
Name: pykolofinance
Version: 5.0.5
Summary: A utility package for kolomoni banking microservices
Author: Daniel Ale
Author-email: danielale9291@gmail.com
Requires-Python: >=3.11,<4.0
Classifier: Programming Language :: Python :: 3
Classifier: Programming Language :: Python :: 3.11
Classifier: Programming Language :: Python :: 3.12
Classifier: Programming Language :: Python :: 3.13
Requires-Dist: cuid2 (>=2.0.1,<3.0.0)
Requires-Dist: django-filter (>=25.1,<26.0)
Requires-Dist: djangorestframework (>=3.16.0,<4.0.0)
Requires-Dist: djangorestframework-simplejwt (>=5.5.0,<6.0.0)
Requires-Dist: drf-spectacular (>=0.28.0,<0.29.0)
Requires-Dist: elasticsearch (>=8.17.2,<9.0.0)
Requires-Dist: faker (>=37.1.0,<38.0.0)
Requires-Dist: pymongo[srv] (>=4.10.1,<5.0.0)
Requires-Dist: python-logstash-async (>=4.0.2,<5.0.0)
Requires-Dist: redis (>=6.0.0,<7.0.0)
Requires-Dist: requests (>=2.32.3,<3.0.0)
Requires-Dist: sentry-sdk (>=2.25.1,<3.0.0)
